{
  "pmid": "19208012",
  "title": "Activities related to the occurrence of traumatic dental injuries in 15- to 18-year-olds.",
  "abstract": "OBJECTIVE: To assess the activities related to the occurrence of traumatic dental injuries (TDI) in order to establish the relationship between gender, socio-economic status (SES) and major TDI related events, using classification and examination procedures suitable for epidemiological purposes, in a sample of 15- to 18-year-old students in Taiwan.\nMETHODS: A random sample of 6312 15- to 18-year-old senior high school students in southern Taiwan was selected. Each was examined with standard clinical procedures and a questionnaire.\nRESULTS: The prevalence of TDI was 19.9%. The major TDI related events included sports and leisure activities (30.8%), eating (20.5%), falls (19.4%), traffic accidents (10.2%) and collisions (7.1%). Within TDI victims, sports and leisure related TDI were more prevalent among males (P = 0.001, OR = 1.640, 95% CI = 1.225, 2.195) and high SES adolescents (P = 0.014, OR = 1.991, 95% CI = 1.149, 3.449). The occurrence of non-accidental TDI was not related to age, gender and SES (P > or = 0.643).\nCONCLUSION: Traumatic dental injuries have become an important issue in public health and dentistry. Prevention and treatment of TDI should be emphasised to the public, the health professional and the policy maker. Future investigations into the relationship between TDI related events and their determinants are indicated.",
  "publication_types": [
    "Journal Article"
  ],
  "mesh": [
    "Accidental Falls",
    "Accidents, Traffic",
    "Adolescent",
    "Athletic Injuries",
    "Cross-Sectional Studies",
    "Eating",
    "Female",
    "Humans",
    "Leisure Activities",
    "Male",
    "Sex Factors",
    "Social Class",
    "Taiwan",
    "Tooth Injuries"
  ],
  "language": "eng",
  "pub_year": "2009",
  "journal": "Dental traumatology : official publication of International Association for Dental Traumatology",
  "authors": [
    "Huang B",
    "Marcenes W",
    "Croucher R",
    "Hector M"
  ]
}