{
  "pmid": "26545273",
  "title": "Mandatory mouthguard rules for high school athletes in the United States.",
  "abstract": "High school athletes seem particularly predisposed to dental injury, but athletic mouthguards have an excellent track record of success in reducing the severity and incidence of dental injuries in sports. Therefore, it has been suggested that mouthguards be made mandatory for high school athletes who participate in sports with risk of injury. The National Federation of State High School Associations currently recommends that mouthguards be mandated for high school football, lacrosse, ice hockey, and field hockey players as well as for wrestlers who are wearing orthodontic appliances. Different states have tried to mandate additional sports with varying degrees of success. This article summarizes the process that leads to rule changes for high school athletes at the national level and discusses the history of 4 states--Minnesota, Maine, New Hampshire, and Massachusetts--that have tried to mandate mouthguards for different sports. Common complaints that lead to the cessation of mouthguard rules, such as speech considerations, breathing ability, and cleanliness, are discussed.",
  "publication_types": [
    "Journal Article"
  ],
  "mesh": [
    "Adolescent",
    "Athletes",
    "Athletic Injuries",
    "Female",
    "Humans",
    "Maine",
    "Male",
    "Mandatory Programs",
    "Massachusetts",
    "Minnesota",
    "Mouth Protectors",
    "New Hampshire",
    "Schools",
    "Sports",
    "Tooth Injuries",
    "United States"
  ],
  "language": "eng",
  "pub_year": "2015",
  "journal": "General dentistry",
  "authors": [
    "Mills SC"
  ]
}